nitro/CHANGELOG.md
nitro/__init__.py
nitro/__init__.pyi
nitro/config.py
nitro/utils.py
nitro/adapters/__init__.py
nitro/adapters/fastapi.py
nitro/adapters/fasthtml.py
nitro/adapters/flask.py
nitro/application/__init__.py
nitro/application/cli/__init__.py
nitro/application/cli/main.py
nitro/application/cli/utils.py
nitro/application/cli/database_commands/__init__.py
nitro/application/cli/database_commands/cli.py
nitro/application/cli/database_commands/templates/README
nitro/application/cli/database_commands/templates/__init__.py
nitro/application/cli/database_commands/templates/alembic.ini.mako
nitro/application/cli/database_commands/templates/env.py
nitro/application/cli/database_commands/templates/script.py.mako
nitro/application/cli/tailwind_commands/__init__.py
nitro/application/cli/tailwind_commands/build.py
nitro/application/cli/tailwind_commands/dev.py
nitro/application/cli/tailwind_commands/init.py
nitro/application/tailwind_builder/__init__.py
nitro/application/tailwind_builder/binary.py
nitro/application/tailwind_builder/builder.py
nitro/application/templates/__init__.py
nitro/application/templates/app_starter.py
nitro/application/templates/css_input.py
nitro/application/templates/css/input.css
nitro/application/templates/css/basecoat/basecoat.all.css
nitro/application/templates/css/basecoat/basecoat.cdn.css
nitro/application/templates/css/basecoat/basecoat.css
nitro/application/templates/css/basecoat/themes.css
nitro/application/templates/css/basecoat/base/base.css
nitro/application/templates/css/basecoat/components/accordion.css
nitro/application/templates/css/basecoat/components/alert.css
nitro/application/templates/css/basecoat/components/badge.css
nitro/application/templates/css/basecoat/components/base.css
nitro/application/templates/css/basecoat/components/button-group.css
nitro/application/templates/css/basecoat/components/button.css
nitro/application/templates/css/basecoat/components/card.css
nitro_boost-0.2.2.dist-info/METADATA
nitro_boost-0.2.2.dist-info/WHEEL
nitro_boost-0.2.2.dist-info/entry_points.txt
nitro_boost-0.2.2.dist-info/RECORD
