Metadata-Version: 2.4
Name: nitro-boost
Version: 0.2.2
Summary: Add your description here
Author-email: ndendic <ndendic@gmail.com>
Requires-Python: >=3.10
Requires-Dist: blinker>=1.9.0
Requires-Dist: pydantic-settings>=2.11.0
Requires-Dist: pydantic>=2.11.9
Requires-Dist: requests>=2.32.5
Requires-Dist: rusty-tags>=0.6.3
Requires-Dist: typer>=0.19.2
